{
  "label": "Mistral-7B",
  "janModelId": "Mistral-7B-Instruct-v0_3_IQ4_XS",
  "timestamp": "2026-03-23T10:37:11.949Z",
  "results": {
    "E1": {
      "experimentId": "E1-consensus-formation",
      "durationMs": 108898,
      "rounds": 10,
      "totalCommits": 300,
      "totalReveals": 300,
      "totalContributions": 5,
      "verdictAccuracyRate": 0.8533333333333334,
      "revealSuccessRate": 1,
      "meanConsensusLatencyRounds": 1,
      "reputationGini": 0.18305084745762712,
      "blacklistRate": 0,
      "graduationRate": 1,
      "meanFinalConfidence": 0.5040425531914894,
      "reputationByAccuracy": {
        "correctMean": 1,
        "incorrectMean": -10
      }
    },
    "E2": {
      "experimentId": "E2-adversarial-detection",
      "durationMs": 131295,
      "rounds": 15,
      "totalCommits": 366,
      "totalReveals": 366,
      "totalContributions": 5,
      "verdictAccuracyRate": 0.8306010928961749,
      "revealSuccessRate": 1,
      "meanConsensusLatencyRounds": 1,
      "reputationGini": 0.27912087912087913,
      "blacklistRate": 0.2,
      "graduationRate": 0.8,
      "meanFinalConfidence": 0.5093939393939394,
      "reputationByAccuracy": {
        "correctMean": 1,
        "incorrectMean": -10
      }
    },
    "E7": {
      "experimentId": "E7-contradiction-injection",
      "durationMs": 13261,
      "rounds": 12,
      "totalCommits": 246,
      "totalReveals": 246,
      "totalContributions": 2,
      "verdictAccuracyRate": 0.9105691056910569,
      "revealSuccessRate": 1,
      "meanConsensusLatencyRounds": 1,
      "reputationGini": 0.29500580720092917,
      "blacklistRate": 0.2857142857142857,
      "graduationRate": 1,
      "meanFinalConfidence": 0.43625,
      "reputationByAccuracy": {
        "correctMean": 1,
        "incorrectMean": -10
      }
    }
  }
}